MANIFEST.in
README.md
setup.py
Djformtags.egg-info/PKG-INFO
Djformtags.egg-info/SOURCES.txt
Djformtags.egg-info/dependency_links.txt
Djformtags.egg-info/not-zip-safe
Djformtags.egg-info/top_level.txt
djformtags/__init__.py
djformtags/tests.py
djformtags/util.py
djformtags.egg-info/SOURCES.txt
djformtags/templatetags/__init__.py
djformtags/templatetags/formtags.py