Metadata-Version: 1.0
Name: djformtags
Version: 1.0
Summary: Simplifies and enhance form rendering in Django templates.
Home-page: https://github.com/prestontimmons/djformtags
Author: Preston Timmons
Author-email: prestontimmons@gmail.com
License: UNKNOWN
Platform: UNKNOWN
